bob3client/__init__.py
bob3client/main.py
bob3client-0.0.1.dist-info/METADATA
bob3client-0.0.1.dist-info/WHEEL
bob3client-0.0.1.dist-info/top_level.txt
bob3client-0.0.1.dist-info/RECORD
