Metadata-Version: 2.1
Name: bob3client
Version: 0.0.1
Summary: Lightweight bob3 client utilities
Author-email: Juris Kaminskis <juris.kaminskis@gmail.com>
Project-URL: Repository, https://bitbucket.org/u9/3061-bob-3-0/src/develop/
Keywords: bob3,projects
Classifier: Development Status :: 3 - Alpha
Classifier: Intended Audience :: Developers
Classifier: License :: OSI Approved :: MIT License
Classifier: Programming Language :: Python :: 3
Classifier: Programming Language :: Python :: 3.9
Classifier: Programming Language :: Python :: 3.10
Requires-Python: >=3.11
Requires-Dist: joserfc >=0.9.0
